src/wb_wdt/EF_WDT32/EF_WDT32.v
/*
	Copyright 2024 Efabless Corp.

	Author: Efabless Corp. (ip_admin@efabless.com)

	Licensed under the Apache License, Version 2.0 (the "License");
	you may not use this file except in compliance with the License.
	You may obtain a copy of the License at

	    http://www.apache.org/licenses/LICENSE-2.0

	Unless required by applicable law or agreed to in writing, software
	distributed under the License is distributed on an "AS IS" BASIS,
	WITHOUT WARRANTIES OR CONDITIONS OF ANY KIND, either express or implied.
	See the License for the specific language governing permissions and
	limitations under the License.

*/

/*MOD BY DATDT (datiuemm) in 2026
  HAVE A NICE DAY*/

`timescale          1ns/1ps
`default_nettype    none

module EF_WDT32 (
		input wire          clk,
		input wire          rst_i,
		input wire          WDTEN, // = 1 Enable
		input wire [31:0]   WDTLOAD, //Reload Value
		input wire			WDTFEED,

		output reg         WDTTO, //TimeOut
		output reg [31:0]   WDTMR //Timer

);

	//assign	WDTTO = WDTEN & (WDTMR == 32'd0);
	wire rst_n = ~rst_i;
	// WDTimer
	always @(posedge clk or negedge rst_n)
	begin
		if(!rst_n) begin
			WDTMR <= 32'h0000_0000;
			WDTTO <= 0;
		end
		else if(WDTEN == 1'b0)
			WDTMR <= WDTLOAD;
		else if (WDTFEED == 1'b1 && WDTEN == 1'b1)
			WDTMR <= WDTLOAD;
		else if(WDTTO == 1'b1)
			WDTMR <= WDTLOAD;
		else 
			WDTMR <= WDTMR - 32'd1;
		
		WDTTO <= WDTEN & (WDTMR == 32'd0);
	end

endmodule

tb/wb_wdt/EF_WDT32/tb_EF_WDT32.sv
`timescale 1ns/1ps

//`include "EF_WDT32.v"
`default_nettype none


//This test will basic test submodule
module tb_EF_WDT32;
reg clk;
reg rst_i;
reg WDTEN;
reg [31:0] WDTLOAD;
reg WDTTO;
reg [31:0] WDTMR;
reg [31:0] reg_WDTMR;
reg WDTFEED;
integer fail;

EF_WDT32 dut
(
    .rst_i (rst_i),
    .clk (clk),
    .WDTEN (WDTEN), 
    .WDTLOAD (WDTLOAD), 
    .WDTTO (WDTTO), 
    .WDTMR (WDTMR),
    .WDTFEED (WDTFEED)
);

localparam CLK_PERIOD = 10;
always #(CLK_PERIOD/2) clk=~clk;

initial begin
    $dumpfile("tb_EF_WDT32.vcd");
    $dumpvars(0, tb_EF_WDT32);
end

initial begin
    //init
    fail = 0;
    clk = 1;
    rst_i = 1;
    WDTEN = 0;
    WDTLOAD = 32'h0000_0000;
    #10;
    WDTFEED = 0;
    rst_i = 0;

    /*
    //EN first then reload
    WDTEN = 1;
    #10;
    WDTLOAD = 32'hDEAD_BEEF;
    #50;
    reg_WDTMR = WDTMR;
    $display("WDTMR = 0x%h", reg_WDTMR);
    if (reg_WDTMR !== WDTLOAD) begin
        $display("------Test Passed, WDT is running------");
    end 
    else begin
        $display("\nFAILED");
        fail ++;
    end

    #50;


    //EN = 0, WDT will not running
    rst_i = 1;
    WDTEN = 0; //Test submodule, reg will store 1 from the last value, reset value off EN are on wrapper
    #10;
    rst_i = 0;
    //WDTEN = 1;
    #10;
    WDTLOAD = 32'hBABA_CACA;
    #50;
    reg_WDTMR = WDTMR;
    $display("WDTMR = 0x%h", reg_WDTMR);
    if (reg_WDTMR == WDTLOAD) begin
        $display("-----Test Passed, WDT is not running------");
    end 
    else begin
        $display("\nFAILED");
        fail ++;
    end

    #50;

    //Test reset
    rst_i = 1;
    WDTEN = 0; //Test submodule, reg will store 1 from the last value, reset value off EN are on wrapper
    #10;
    rst_i = 0;
    WDTEN = 1;
    #10;
    WDTLOAD = 32'hCABA_CACA;
    #50;
    reg_WDTMR = WDTMR;
    $display("WDTMR = 0x%h", reg_WDTMR);
    if (reg_WDTMR !== WDTLOAD) begin
        $display("-----Test Passed, WDT is running------");
    end 
    else begin
        $display("\nFAILED");
        fail++;
    end

    #50;


    //This test will load value first then enable 
    rst_i = 1;
    WDTEN = 0; //Test submodule, reg will store 1 from the last value, reset value off EN are on wrapper
    #10;
    rst_i = 0;
    WDTLOAD = 32'hCABA_CACA;
    #10;
    WDTEN = 1;
    #50;
    reg_WDTMR = WDTMR;
    $display("WDTMR = 0x%h", reg_WDTMR);
    if (reg_WDTMR !== WDTLOAD) begin
        $display("-----Test Passed, WDT is running------");
    end 
    else begin
        $display("\nFAILED");
        fail++;
    end

*/
/*
    rst_i = 1;
    WDTEN = 0; //Test submodule, reg will store 1 from the last value, reset value off EN are on wrapper
    #10;
    rst_i = 0;
    WDTLOAD = 32'hACAC_CACA;
    #10;
    WDTEN = 1;
    #100;
    reg_WDTMR = WDTMR;
    $display("WDTMR = 0x%h", reg_WDTMR);
    if (reg_WDTMR !== WDTLOAD) begin
        $display("-----Test Passed, WDT is running------");
    end 
    else begin
        $display("\nFAILED");
        fail++;
    end

    #100;
    WDTLOAD = 32'hFFFF_FAFFF;
    WDTFEED = 1'b1;
    #10;
    WDTFEED = 1'b0;
    #100;
    reg_WDTMR = WDTMR;
    $display("WDTMR = 0x%h", reg_WDTMR);
    if (reg_WDTMR !== WDTLOAD && reg_WDTMR < 32'hFFFF_FAFFF && reg_WDTMR > 32'hACAC_CACA) begin
        $display("-----Test Passed, WDT is running Current Value 0x%h------", reg_WDTMR);
    end 
    else begin
        $display("\nFAILED");
        fail++;
    end
*/

/*
    rst_i = 1;
    WDTEN = 0; //Test submodule, reg will store 1 from the last value, reset value off EN are on wrapper
    #10;
    rst_i = 0;
    WDTLOAD = 32'h0000_00100;
    #10;
    WDTEN = 1;
    #100;
    reg_WDTMR = WDTMR;
    $display("WDTMR = 0x%h", reg_WDTMR);
    if (reg_WDTMR !== WDTLOAD) begin
        $display("-----Test Passed, WDT is running------");
    end 
    else begin
        $display("\nFAILED");
        fail++;
    end

    wait (WDTMR == 32'h0000_00008);
    //WDTLOAD = 32'hFFFF_FAFFF;
    WDTFEED = 1'b1;
    #10;
    WDTFEED = 1'b0;
    #100;
    reg_WDTMR = WDTMR;
    $display("WDTMR = 0x%h", reg_WDTMR);
    if (reg_WDTMR !== WDTLOAD && reg_WDTMR < 32'h0000_00100 && reg_WDTMR > 32'h0000_0001) begin
        $display("-----Test Passed, WDT is running Current Value 0x%h------", reg_WDTMR);
    end 
    else begin
        $display("\nFAILED");
        fail++;
    end
*/


    rst_i = 1;
    WDTEN = 0; //Test submodule, reg will store 1 from the last value, reset value off EN are on wrapper
    #10;
    rst_i = 0;
    WDTLOAD = 32'h0000_00100;
    #10;
    WDTEN = 1;
    #90;
    reg_WDTMR = WDTMR;
    $display("WDTMR = 0x%h", reg_WDTMR);
    if (reg_WDTMR !== WDTLOAD) begin
        $display("-----Test Passed, WDT is running------");
    end 
    else begin
        $display("\nFAILED");
        fail++;
    end

    wait (WDTMR == 32'h0000_00001);
    #10;
    $display("WDTTO = 0x%h", WDTTO);
    //WDTLOAD = 32'hFFFF_FAFFF;
    WDTFEED = 1'b1;
    #10;
    WDTFEED = 1'b0;
    #100;
    reg_WDTMR = WDTMR;
    $display("WDTMR = 0x%h", reg_WDTMR);
    $display("WDTTO = 0x%h", WDTTO);
    if (reg_WDTMR !== WDTLOAD && reg_WDTMR < 32'h0000_00100 && reg_WDTMR > 32'h0000_0001) begin
        $display("-----Test Passed, WDT is running Current Value 0x%h------", reg_WDTMR);
    end 
    else begin
        $display("\nFAILED");
        fail++;
    end 

    #50;


    

    if (fail == 0) begin
        $display("\n\n-----All Test Passed------");
    end 
    else begin
        $display("FAILED");
    end

    $finish;
end

endmodule

run/scripts/tb_EF_WDT32.vcd
$date
	Fri Feb 20 12:42:36 2026
$end
$version
	QuestaSim Version 2021.2_1
$end
$timescale
	1ps
$end

$scope module tb_EF_WDT32 $end
$var parameter 32 ! CLK_PERIOD $end
$var reg 1 " clk $end
$var reg 1 # rst_i $end
$var reg 1 $ WDTEN $end
$var reg 32 % WDTLOAD [31:0] $end
$var reg 1 & WDTTO $end
$var reg 32 ' WDTMR [31:0] $end
$var reg 32 ( reg_WDTMR [31:0] $end
$var reg 1 ) WDTFEED $end
$var integer 32 * fail $end

$scope module dut $end
$var wire 1 + clk $end
$var wire 1 , rst_i $end
$var wire 1 - WDTEN $end
$var wire 1 . WDTLOAD [31] $end
$var wire 1 / WDTLOAD [30] $end
$var wire 1 0 WDTLOAD [29] $end
$var wire 1 1 WDTLOAD [28] $end
$var wire 1 2 WDTLOAD [27] $end
$var wire 1 3 WDTLOAD [26] $end
$var wire 1 4 WDTLOAD [25] $end
$var wire 1 5 WDTLOAD [24] $end
$var wire 1 6 WDTLOAD [23] $end
$var wire 1 7 WDTLOAD [22] $end
$var wire 1 8 WDTLOAD [21] $end
$var wire 1 9 WDTLOAD [20] $end
$var wire 1 : WDTLOAD [19] $end
$var wire 1 ; WDTLOAD [18] $end
$var wire 1 < WDTLOAD [17] $end
$var wire 1 = WDTLOAD [16] $end
$var wire 1 > WDTLOAD [15] $end
$var wire 1 ? WDTLOAD [14] $end
$var wire 1 @ WDTLOAD [13] $end
$var wire 1 A WDTLOAD [12] $end
$var wire 1 B WDTLOAD [11] $end
$var wire 1 C WDTLOAD [10] $end
$var wire 1 D WDTLOAD [9] $end
$var wire 1 E WDTLOAD [8] $end
$var wire 1 F WDTLOAD [7] $end
$var wire 1 G WDTLOAD [6] $end
$var wire 1 H WDTLOAD [5] $end
$var wire 1 I WDTLOAD [4] $end
$var wire 1 J WDTLOAD [3] $end
$var wire 1 K WDTLOAD [2] $end
$var wire 1 L WDTLOAD [1] $end
$var wire 1 M WDTLOAD [0] $end
$var wire 1 N WDTFEED $end
$var reg 1 O WDTTO $end
$var reg 32 P WDTMR [31:0] $end
$var wire 1 Q rst_n $end
$upscope $end
$upscope $end
$enddefinitions $end
#0
$dumpvars
1"
1#
0$
b0 %
0&
b0 '
bx (
x)
0O
b0 P
b1010 !
b0 *
0Q
xN
0M
0L
0K
0J
0I
0H
0G
0F
0E
0D
0C
0B
0A
0@
0?
0>
0=
0<
0;
0:
09
08
07
06
05
04
03
02
01
00
0/
0.
0-
1,
1+
$end
#5000
0"
0+
#10000
0)
0#
1#
1"
0N
1+
#15000
0"
0+
#20000
0#
b100000000 %
1"
0,
1E
1+
1Q
b100000000 P
b100000000 '
#25000
0"
0+
#30000
1$
1"
1-
1+
b11111111 P
b11111111 '
#35000
0"
0+
#40000
1"
1+
b11111110 P
b11111110 '
#45000
0"
0+
#50000
1"
1+
b11111101 P
b11111101 '
#55000
0"
0+
#60000
1"
1+
b11111100 P
b11111100 '
#65000
0"
0+
#70000
1"
1+
b11111011 P
b11111011 '
#75000
0"
0+
#80000
1"
1+
b11111010 P
b11111010 '
#85000
0"
0+
#90000
1"
1+
b11111001 P
b11111001 '
#95000
0"
0+
#100000
1"
1+
b11111000 P
b11111000 '
#105000
0"
0+
#110000
1"
1+
b11110111 P
b11110111 '
#115000
0"
0+
#120000
b11110111 (
1"
1+
b11110110 P
b11110110 '
#125000
0"
0+
#130000
1"
1+
b11110101 P
b11110101 '
#135000
0"
0+
#140000
1"
1+
b11110100 P
b11110100 '
#145000
0"
0+
#150000
1"
1+
b11110011 P
b11110011 '
#155000
0"
0+
#160000
1"
1+
b11110010 P
b11110010 '
#165000
0"
0+
#170000
1"
1+
b11110001 P
b11110001 '
#175000
0"
0+
#180000
1"
1+
b11110000 P
b11110000 '
#185000
0"
0+
#190000
1"
1+
b11101111 P
b11101111 '
#195000
0"
0+
#200000
1"
1+
b11101110 P
b11101110 '
#205000
0"
0+
#210000
1"
1+
b11101101 P
b11101101 '
#215000
0"
0+
#220000
1"
1+
b11101100 P
b11101100 '
#225000
0"
0+
#230000
1"
1+
b11101011 P
b11101011 '
#235000
0"
0+
#240000
1"
1+
b11101010 P
b11101010 '
#245000
0"
0+
#250000
1"
1+
b11101001 P
b11101001 '
#255000
0"
0+
#260000
1"
1+
b11101000 P
b11101000 '
#265000
0"
0+
#270000
1"
1+
b11100111 P
b11100111 '
#275000
0"
0+
#280000
1"
1+
b11100110 P
b11100110 '
#285000
0"
0+
#290000
1"
1+
b11100101 P
b11100101 '
#295000
0"
0+
#300000
1"
1+
b11100100 P
b11100100 '
#305000
0"
0+
#310000
1"
1+
b11100011 P
b11100011 '
#315000
0"
0+
#320000
1"
1+
b11100010 P
b11100010 '
#325000
0"
0+
#330000
1"
1+
b11100001 P
b11100001 '
#335000
0"
0+
#340000
1"
1+
b11100000 P
b11100000 '
#345000
0"
0+
#350000
1"
1+
b11011111 P
b11011111 '
#355000
0"
0+
#360000
1"
1+
b11011110 P
b11011110 '
#365000
0"
0+
#370000
1"
1+
b11011101 P
b11011101 '
#375000
0"
0+
#380000
1"
1+
b11011100 P
b11011100 '
#385000
0"
0+
#390000
1"
1+
b11011011 P
b11011011 '
#395000
0"
0+
#400000
1"
1+
b11011010 P
b11011010 '
#405000
0"
0+
#410000
1"
1+
b11011001 P
b11011001 '
#415000
0"
0+
#420000
1"
1+
b11011000 P
b11011000 '
#425000
0"
0+
#430000
1"
1+
b11010111 P
b11010111 '
#435000
0"
0+
#440000
1"
1+
b11010110 P
b11010110 '
#445000
0"
0+
#450000
1"
1+
b11010101 P
b11010101 '
#455000
0"
0+
#460000
1"
1+
b11010100 P
b11010100 '
#465000
0"
0+
#470000
1"
1+
b11010011 P
b11010011 '
#475000
0"
0+
#480000
1"
1+
b11010010 P
b11010010 '
#485000
0"
0+
#490000
1"
1+
b11010001 P
b11010001 '
#495000
0"
0+
#500000
1"
1+
b11010000 P
b11010000 '
#505000
0"
0+
#510000
1"
1+
b11001111 P
b11001111 '
#515000
0"
0+
#520000
1"
1+
b11001110 P
b11001110 '
#525000
0"
0+
#530000
1"
1+
b11001101 P
b11001101 '
#535000
0"
0+
#540000
1"
1+
b11001100 P
b11001100 '
#545000
0"
0+
#550000
1"
1+
b11001011 P
b11001011 '
#555000
0"
0+
#560000
1"
1+
b11001010 P
b11001010 '
#565000
0"
0+
#570000
1"
1+
b11001001 P
b11001001 '
#575000
0"
0+
#580000
1"
1+
b11001000 P
b11001000 '
#585000
0"
0+
#590000
1"
1+
b11000111 P
b11000111 '
#595000
0"
0+
#600000
1"
1+
b11000110 P
b11000110 '
#605000
0"
0+
#610000
1"
1+
b11000101 P
b11000101 '
#615000
0"
0+
#620000
1"
1+
b11000100 P
b11000100 '
#625000
0"
0+
#630000
1"
1+
b11000011 P
b11000011 '
#635000
0"
0+
#640000
1"
1+
b11000010 P
b11000010 '
#645000
0"
0+
#650000
1"
1+
b11000001 P
b11000001 '
#655000
0"
0+
#660000
1"
1+
b11000000 P
b11000000 '
#665000
0"
0+
#670000
1"
1+
b10111111 P
b10111111 '
#675000
0"
0+
#680000
1"
1+
b10111110 P
b10111110 '
#685000
0"
0+
#690000
1"
1+
b10111101 P
b10111101 '
#695000
0"
0+
#700000
1"
1+
b10111100 P
b10111100 '
#705000
0"
0+
#710000
1"
1+
b10111011 P
b10111011 '
#715000
0"
0+
#720000
1"
1+
b10111010 P
b10111010 '
#725000
0"
0+
#730000
1"
1+
b10111001 P
b10111001 '
#735000
0"
0+
#740000
1"
1+
b10111000 P
b10111000 '
#745000
0"
0+
#750000
1"
1+
b10110111 P
b10110111 '
#755000
0"
0+
#760000
1"
1+
b10110110 P
b10110110 '
#765000
0"
0+
#770000
1"
1+
b10110101 P
b10110101 '
#775000
0"
0+
#780000
1"
1+
b10110100 P
b10110100 '
#785000
0"
0+
#790000
1"
1+
b10110011 P
b10110011 '
#795000
0"
0+
#800000
1"
1+
b10110010 P
b10110010 '
#805000
0"
0+
#810000
1"
1+
b10110001 P
b10110001 '
#815000
0"
0+
#820000
1"
1+
b10110000 P
b10110000 '
#825000
0"
0+
#830000
1"
1+
b10101111 P
b10101111 '
#835000
0"
0+
#840000
1"
1+
b10101110 P
b10101110 '
#845000
0"
0+
#850000
1"
1+
b10101101 P
b10101101 '
#855000
0"
0+
#860000
1"
1+
b10101100 P
b10101100 '
#865000
0"
0+
#870000
1"
1+
b10101011 P
b10101011 '
#875000
0"
0+
#880000
1"
1+
b10101010 P
b10101010 '
#885000
0"
0+
#890000
1"
1+
b10101001 P
b10101001 '
#895000
0"
0+
#900000
1"
1+
b10101000 P
b10101000 '
#905000
0"
0+
#910000
1"
1+
b10100111 P
b10100111 '
#915000
0"
0+
#920000
1"
1+
b10100110 P
b10100110 '
#925000
0"
0+
#930000
1"
1+
b10100101 P
b10100101 '
#935000
0"
0+
#940000
1"
1+
b10100100 P
b10100100 '
#945000
0"
0+
#950000
1"
1+
b10100011 P
b10100011 '
#955000
0"
0+
#960000
1"
1+
b10100010 P
b10100010 '
#965000
0"
0+
#970000
1"
1+
b10100001 P
b10100001 '
#975000
0"
0+
#980000
1"
1+
b10100000 P
b10100000 '
#985000
0"
0+
#990000
1"
1+
b10011111 P
b10011111 '
#995000
0"
0+
#1000000
1"
1+
b10011110 P
b10011110 '
#1005000
0"
0+
#1010000
1"
1+
b10011101 P
b10011101 '
#1015000
0"
0+
#1020000
1"
1+
b10011100 P
b10011100 '
#1025000
0"
0+
#1030000
1"
1+
b10011011 P
b10011011 '
#1035000
0"
0+
#1040000
1"
1+
b10011010 P
b10011010 '
#1045000
0"
0+
#1050000
1"
1+
b10011001 P
b10011001 '
#1055000
0"
0+
#1060000
1"
1+
b10011000 P
b10011000 '
#1065000
0"
0+
#1070000
1"
1+
b10010111 P
b10010111 '
#1075000
0"
0+
#1080000
1"
1+
b10010110 P
b10010110 '
#1085000
0"
0+
#1090000
1"
1+
b10010101 P
b10010101 '
#1095000
0"
0+
#1100000
1"
1+
b10010100 P
b10010100 '
#1105000
0"
0+
#1110000
1"
1+
b10010011 P
b10010011 '
#1115000
0"
0+
#1120000
1"
1+
b10010010 P
b10010010 '
#1125000
0"
0+
#1130000
1"
1+
b10010001 P
b10010001 '
#1135000
0"
0+
#1140000
1"
1+
b10010000 P
b10010000 '
#1145000
0"
0+
#1150000
1"
1+
b10001111 P
b10001111 '
#1155000
0"
0+
#1160000
1"
1+
b10001110 P
b10001110 '
#1165000
0"
0+
#1170000
1"
1+
b10001101 P
b10001101 '
#1175000
0"
0+
#1180000
1"
1+
b10001100 P
b10001100 '
#1185000
0"
0+
#1190000
1"
1+
b10001011 P
b10001011 '
#1195000
0"
0+
#1200000
1"
1+
b10001010 P
b10001010 '
#1205000
0"
0+
#1210000
1"
1+
b10001001 P
b10001001 '
#1215000
0"
0+
#1220000
1"
1+
b10001000 P
b10001000 '
#1225000
0"
0+
#1230000
1"
1+
b10000111 P
b10000111 '
#1235000
0"
0+
#1240000
1"
1+
b10000110 P
b10000110 '
#1245000
0"
0+
#1250000
1"
1+
b10000101 P
b10000101 '
#1255000
0"
0+
#1260000
1"
1+
b10000100 P
b10000100 '
#1265000
0"
0+
#1270000
1"
1+
b10000011 P
b10000011 '
#1275000
0"
0+
#1280000
1"
1+
b10000010 P
b10000010 '
#1285000
0"
0+
#1290000
1"
1+
b10000001 P
b10000001 '
#1295000
0"
0+
#1300000
1"
1+
b10000000 P
b10000000 '
#1305000
0"
0+
#1310000
1"
1+
b1111111 P
b1111111 '
#1315000
0"
0+
#1320000
1"
1+
b1111110 P
b1111110 '
#1325000
0"
0+
#1330000
1"
1+
b1111101 P
b1111101 '
#1335000
0"
0+
#1340000
1"
1+
b1111100 P
b1111100 '
#1345000
0"
0+
#1350000
1"
1+
b1111011 P
b1111011 '
#1355000
0"
0+
#1360000
1"
1+
b1111010 P
b1111010 '
#1365000
0"
0+
#1370000
1"
1+
b1111001 P
b1111001 '
#1375000
0"
0+
#1380000
1"
1+
b1111000 P
b1111000 '
#1385000
0"
0+
#1390000
1"
1+
b1110111 P
b1110111 '
#1395000
0"
0+
#1400000
1"
1+
b1110110 P
b1110110 '
#1405000
0"
0+
#1410000
1"
1+
b1110101 P
b1110101 '
#1415000
0"
0+
#1420000
1"
1+
b1110100 P
b1110100 '
#1425000
0"
0+
#1430000
1"
1+
b1110011 P
b1110011 '
#1435000
0"
0+
#1440000
1"
1+
b1110010 P
b1110010 '
#1445000
0"
0+
#1450000
1"
1+
b1110001 P
b1110001 '
#1455000
0"
0+
#1460000
1"
1+
b1110000 P
b1110000 '
#1465000
0"
0+
#1470000
1"
1+
b1101111 P
b1101111 '
#1475000
0"
0+
#1480000
1"
1+
b1101110 P
b1101110 '
#1485000
0"
0+
#1490000
1"
1+
b1101101 P
b1101101 '
#1495000
0"
0+
#1500000
1"
1+
b1101100 P
b1101100 '
#1505000
0"
0+
#1510000
1"
1+
b1101011 P
b1101011 '
#1515000
0"
0+
#1520000
1"
1+
b1101010 P
b1101010 '
#1525000
0"
0+
#1530000
1"
1+
b1101001 P
b1101001 '
#1535000
0"
0+
#1540000
1"
1+
b1101000 P
b1101000 '
#1545000
0"
0+
#1550000
1"
1+
b1100111 P
b1100111 '
#1555000
0"
0+
#1560000
1"
1+
b1100110 P
b1100110 '
#1565000
0"
0+
#1570000
1"
1+
b1100101 P
b1100101 '
#1575000
0"
0+
#1580000
1"
1+
b1100100 P
b1100100 '
#1585000
0"
0+
#1590000
1"
1+
b1100011 P
b1100011 '
#1595000
0"
0+
#1600000
1"
1+
b1100010 P
b1100010 '
#1605000
0"
0+
#1610000
1"
1+
b1100001 P
b1100001 '
#1615000
0"
0+
#1620000
1"
1+
b1100000 P
b1100000 '
#1625000
0"
0+
#1630000
1"
1+
b1011111 P
b1011111 '
#1635000
0"
0+
#1640000
1"
1+
b1011110 P
b1011110 '
#1645000
0"
0+
#1650000
1"
1+
b1011101 P
b1011101 '
#1655000
0"
0+
#1660000
1"
1+
b1011100 P
b1011100 '
#1665000
0"
0+
#1670000
1"
1+
b1011011 P
b1011011 '
#1675000
0"
0+
#1680000
1"
1+
b1011010 P
b1011010 '
#1685000
0"
0+
#1690000
1"
1+
b1011001 P
b1011001 '
#1695000
0"
0+
#1700000
1"
1+
b1011000 P
b1011000 '
#1705000
0"
0+
#1710000
1"
1+
b1010111 P
b1010111 '
#1715000
0"
0+
#1720000
1"
1+
b1010110 P
b1010110 '
#1725000
0"
0+
#1730000
1"
1+
b1010101 P
b1010101 '
#1735000
0"
0+
#1740000
1"
1+
b1010100 P
b1010100 '
#1745000
0"
0+
#1750000
1"
1+
b1010011 P
b1010011 '
#1755000
0"
0+
#1760000
1"
1+
b1010010 P
b1010010 '
#1765000
0"
0+
#1770000
1"
1+
b1010001 P
b1010001 '
#1775000
0"
0+
#1780000
1"
1+
b1010000 P
b1010000 '
#1785000
0"
0+
#1790000
1"
1+
b1001111 P
b1001111 '
#1795000
0"
0+
#1800000
1"
1+
b1001110 P
b1001110 '
#1805000
0"
0+
#1810000
1"
1+
b1001101 P
b1001101 '
#1815000
0"
0+
#1820000
1"
1+
b1001100 P
b1001100 '
#1825000
0"
0+
#1830000
1"
1+
b1001011 P
b1001011 '
#1835000
0"
0+
#1840000
1"
1+
b1001010 P
b1001010 '
#1845000
0"
0+
#1850000
1"
1+
b1001001 P
b1001001 '
#1855000
0"
0+
#1860000
1"
1+
b1001000 P
b1001000 '
#1865000
0"
0+
#1870000
1"
1+
b1000111 P
b1000111 '
#1875000
0"
0+
#1880000
1"
1+
b1000110 P
b1000110 '
#1885000
0"
0+
#1890000
1"
1+
b1000101 P
b1000101 '
#1895000
0"
0+
#1900000
1"
1+
b1000100 P
b1000100 '
#1905000
0"
0+
#1910000
1"
1+
b1000011 P
b1000011 '
#1915000
0"
0+
#1920000
1"
1+
b1000010 P
b1000010 '
#1925000
0"
0+
#1930000
1"
1+
b1000001 P
b1000001 '
#1935000
0"
0+
#1940000
1"
1+
b1000000 P
b1000000 '
#1945000
0"
0+
#1950000
1"
1+
b111111 P
b111111 '
#1955000
0"
0+
#1960000
1"
1+
b111110 P
b111110 '
#1965000
0"
0+
#1970000
1"
1+
b111101 P
b111101 '
#1975000
0"
0+
#1980000
1"
1+
b111100 P
b111100 '
#1985000
0"
0+
#1990000
1"
1+
b111011 P
b111011 '
#1995000
0"
0+
#2000000
1"
1+
b111010 P
b111010 '
#2005000
0"
0+
#2010000
1"
1+
b111001 P
b111001 '
#2015000
0"
0+
#2020000
1"
1+
b111000 P
b111000 '
#2025000
0"
0+
#2030000
1"
1+
b110111 P
b110111 '
#2035000
0"
0+
#2040000
1"
1+
b110110 P
b110110 '
#2045000
0"
0+
#2050000
1"
1+
b110101 P
b110101 '
#2055000
0"
0+
#2060000
1"
1+
b110100 P
b110100 '
#2065000
0"
0+
#2070000
1"
1+
b110011 P
b110011 '
#2075000
0"
0+
#2080000
1"
1+
b110010 P
b110010 '
#2085000
0"
0+
#2090000
1"
1+
b110001 P
b110001 '
#2095000
0"
0+
#2100000
1"
1+
b110000 P
b110000 '
#2105000
0"
0+
#2110000
1"
1+
b101111 P
b101111 '
#2115000
0"
0+
#2120000
1"
1+
b101110 P
b101110 '
#2125000
0"
0+
#2130000
1"
1+
b101101 P
b101101 '
#2135000
0"
0+
#2140000
1"
1+
b101100 P
b101100 '
#2145000
0"
0+
#2150000
1"
1+
b101011 P
b101011 '
#2155000
0"
0+
#2160000
1"
1+
b101010 P
b101010 '
#2165000
0"
0+
#2170000
1"
1+
b101001 P
b101001 '
#2175000
0"
0+
#2180000
1"
1+
b101000 P
b101000 '
#2185000
0"
0+
#2190000
1"
1+
b100111 P
b100111 '
#2195000
0"
0+
#2200000
1"
1+
b100110 P
b100110 '
#2205000
0"
0+
#2210000
1"
1+
b100101 P
b100101 '
#2215000
0"
0+
#2220000
1"
1+
b100100 P
b100100 '
#2225000
0"
0+
#2230000
1"
1+
b100011 P
b100011 '
#2235000
0"
0+
#2240000
1"
1+
b100010 P
b100010 '
#2245000
0"
0+
#2250000
1"
1+
b100001 P
b100001 '
#2255000
0"
0+
#2260000
1"
1+
b100000 P
b100000 '
#2265000
0"
0+
#2270000
1"
1+
b11111 P
b11111 '
#2275000
0"
0+
#2280000
1"
1+
b11110 P
b11110 '
#2285000
0"
0+
#2290000
1"
1+
b11101 P
b11101 '
#2295000
0"
0+
#2300000
1"
1+
b11100 P
b11100 '
#2305000
0"
0+
#2310000
1"
1+
b11011 P
b11011 '
#2315000
0"
0+
#2320000
1"
1+
b11010 P
b11010 '
#2325000
0"
0+
#2330000
1"
1+
b11001 P
b11001 '
#2335000
0"
0+
#2340000
1"
1+
b11000 P
b11000 '
#2345000
0"
0+
#2350000
1"
1+
b10111 P
b10111 '
#2355000
0"
0+
#2360000
1"
1+
b10110 P
b10110 '
#2365000
0"
0+
#2370000
1"
1+
b10101 P
b10101 '
#2375000
0"
0+
#2380000
1"
1+
b10100 P
b10100 '
#2385000
0"
0+
#2390000
1"
1+
b10011 P
b10011 '
#2395000
0"
0+
#2400000
1"
1+
b10010 P
b10010 '
#2405000
0"
0+
#2410000
1"
1+
b10001 P
b10001 '
#2415000
0"
0+
#2420000
1"
1+
b10000 P
b10000 '
#2425000
0"
0+
#2430000
1"
1+
b1111 P
b1111 '
#2435000
0"
0+
#2440000
1"
1+
b1110 P
b1110 '
#2445000
0"
0+
#2450000
1"
1+
b1101 P
b1101 '
#2455000
0"
0+
#2460000
1"
1+
b1100 P
b1100 '
#2465000
0"
0+
#2470000
1"
1+
b1011 P
b1011 '
#2475000
0"
0+
#2480000
1"
1+
b1010 P
b1010 '
#2485000
0"
0+
#2490000
1"
1+
b1001 P
b1001 '
#2495000
0"
0+
#2500000
1"
1+
b1000 P
b1000 '
#2505000
0"
0+
#2510000
1"
1+
b111 P
b111 '
#2515000
0"
0+
#2520000
1"
1+
b110 P
b110 '
#2525000
0"
0+
#2530000
1"
1+
b101 P
b101 '
#2535000
0"
0+
#2540000
1"
1+
b100 P
b100 '
#2545000
0"
0+
#2550000
1"
1+
b11 P
b11 '
#2555000
0"
0+
#2560000
1"
1+
b10 P
b10 '
#2565000
0"
0+
#2570000
1"
1+
b1 P
b1 '
#2575000
0"
0+
#2580000
1)
1"
1N
1+
b100000000 P
b100000000 '
#2585000
0"
0+
#2590000
0)
1"
0N
1+
b11111111 P
b11111111 '
#2595000
0"
0+
#2600000
1"
1+
b11111110 P
b11111110 '
#2605000
0"
0+
#2610000
1"
1+
b11111101 P
b11111101 '
#2615000
0"
0+
#2620000
1"
1+
b11111100 P
b11111100 '
#2625000
0"
0+
#2630000
1"
1+
b11111011 P
b11111011 '
#2635000
0"
0+
#2640000
1"
1+
b11111010 P
b11111010 '
#2645000
0"
0+
#2650000
1"
1+
b11111001 P
b11111001 '
#2655000
0"
0+
#2660000
1"
1+
b11111000 P
b11111000 '
#2665000
0"
0+
#2670000
1"
1+
b11110111 P
b11110111 '
#2675000
0"
0+
#2680000
1"
1+
b11110110 P
b11110110 '
#2685000
0"
0+
#2690000
b11110110 (
1"
1+
b11110101 P
b11110101 '
#2695000
0"
0+
#2700000
1"
1+
b11110100 P
b11110100 '
#2705000
0"
0+
#2710000
1"
1+
b11110011 P
b11110011 '
#2715000
0"
0+
#2720000
1"
1+
b11110010 P
b11110010 '
#2725000
0"
0+
#2730000
1"
1+
b11110001 P
b11110001 '
