tb/wb_wdt/EF_WDT32/EF_WDT32.v
/*
	Copyright 2024 Efabless Corp.

	Author: Efabless Corp. (ip_admin@efabless.com)

	Licensed under the Apache License, Version 2.0 (the "License");
	you may not use this file except in compliance with the License.
	You may obtain a copy of the License at

	    http://www.apache.org/licenses/LICENSE-2.0

	Unless required by applicable law or agreed to in writing, software
	distributed under the License is distributed on an "AS IS" BASIS,
	WITHOUT WARRANTIES OR CONDITIONS OF ANY KIND, either express or implied.
	See the License for the specific language governing permissions and
	limitations under the License.

*/

`timescale          1ns/1ps
`default_nettype    none

module EF_WDT32 (
		input wire          clk,
		input wire          rst_i,
		input wire          WDTEN, // = 1 Enable
		input wire [31:0]   WDTLOAD, //Reload Value

		output reg         WDTTO, //TimeOut
		output reg [31:0]   WDTMR //Timer

);

	//assign	WDTTO = WDTEN & (WDTMR == 32'd0);
	
	// WDTimer
	always @(posedge clk or negedge rst_i)
	begin
		if(rst_i) begin
			WDTMR <= 32'h0000_0000;
			WDTTO <= 1;
		end
		else if(WDTEN == 1'b0)
			WDTMR <= WDTLOAD;
		else if(WDTTO == 1'b1)
			WDTMR <= WDTLOAD;
		else 
			WDTMR <= WDTMR - 32'd1;
		
		WDTTO <= WDTEN & (WDTMR == 32'd0);
	end

endmodule

tb/wb_wdt/backup_DO NOT USE/tb_EF_WDT32.sv
`timescale 1ns/1ps

`include "EF_WDT32.v"
`default_nettype none


//This test will basic test submodule
module tb_EF_WDT32;
reg clk;
reg rst_i;
reg WDTEN;
reg [31:0] WDTLOAD;
reg WDTTO;
reg [31:0] WDTMR;
reg [31:0] reg_WDTMR;
integer fail;

EF_WDT32 dut
(
    .rst_i (rst_i),
    .clk (clk),
    .WDTEN (WDTEN), 
    .WDTLOAD (WDTLOAD), 
    .WDTTO (WDTTO), 
    .WDTMR (WDTMR) 
);

localparam CLK_PERIOD = 10;
always #(CLK_PERIOD/2) clk=~clk;

initial begin
    $dumpfile("tb_EF_WDT32.vcd");
    $dumpvars(0, tb_EF_WDT32);
end

initial begin
    //init
    fail = 0;
    clk = 1;
    rst_i = 1;
    WDTEN = 0;
    WDTLOAD = 32'h0000_0000;
    #10;
    rst_i = 0;


    //EN first then reload
    WDTEN = 1;
    #10;
    WDTLOAD = 32'hDEAD_BEEF;
    #50;
    reg_WDTMR = WDTMR;
    $display("WDTMR = 0x%h", reg_WDTMR);
    if (reg_WDTMR !== WDTLOAD) begin
        $display("------Test Passed, WDT is running------");
    end 
    else begin
        $display("\nFAILED");
        fail ++;
    end

    #50;


    //EN = 0, WDT will not running
    rst_i = 1;
    WDTEN = 0; //Test submodule, reg will store 1 from the last value, reset value off EN are on wrapper
    #10;
    rst_i = 0;
    //WDTEN = 1;
    #10;
    WDTLOAD = 32'hBABA_CACA;
    #50;
    reg_WDTMR = WDTMR;
    $display("WDTMR = 0x%h", reg_WDTMR);
    if (reg_WDTMR == WDTLOAD) begin
        $display("-----Test Passed, WDT is not running------");
    end 
    else begin
        $display("\nFAILED");
        fail ++;
    end

    #50;

    //Test reset
    rst_i = 1;
    WDTEN = 0; //Test submodule, reg will store 1 from the last value, reset value off EN are on wrapper
    #10;
    rst_i = 0;
    WDTEN = 1;
    #10;
    WDTLOAD = 32'hCABA_CACA;
    #50;
    reg_WDTMR = WDTMR;
    $display("WDTMR = 0x%h", reg_WDTMR);
    if (reg_WDTMR !== WDTLOAD) begin
        $display("-----Test Passed, WDT is running------");
    end 
    else begin
        $display("\nFAILED");
        fail++;
    end

    #50;


    //This test will load value first then enable 
    rst_i = 1;
    WDTEN = 0; //Test submodule, reg will store 1 from the last value, reset value off EN are on wrapper
    #10;
    rst_i = 0;
    WDTLOAD = 32'hCABA_CACA;
    #10;
    WDTEN = 1;
    #50;
    reg_WDTMR = WDTMR;
    $display("WDTMR = 0x%h", reg_WDTMR);
    if (reg_WDTMR !== WDTLOAD) begin
        $display("-----Test Passed, WDT is running------");
    end 
    else begin
        $display("\nFAILED");
        fail++;
    end

    #50;

    if (fail == 0) begin
        $display("\n\n-----All Test Passed------");
    end 
    else begin
        $display("FAILED");
    end

    $finish;
end

endmodule

tb/wb_wdt/backup_DO NOT USE/EF_WDT32/tb_EF_WDT32.vcd
$date
	Wed Feb 18 13:30:57 2026
$end
$version
	QuestaSim Version 2021.2_1
$end
$timescale
	1ps
$end

$scope module tb_EF_WDT32 $end
$var parameter 32 ! CLK_PERIOD $end
$var reg 1 " clk $end
$var reg 1 # rst_i $end
$var reg 1 $ WDTEN $end
$var reg 32 % WDTLOAD [31:0] $end
$var reg 1 & WDTTO $end
$var reg 32 ' WDTMR [31:0] $end
$var reg 32 ( reg_WDTMR [31:0] $end
$var integer 32 ) fail $end

$scope module dut $end
$var wire 1 * clk $end
$var wire 1 + rst_i $end
$var wire 1 , WDTEN $end
$var wire 1 - WDTLOAD [31] $end
$var wire 1 . WDTLOAD [30] $end
$var wire 1 / WDTLOAD [29] $end
$var wire 1 0 WDTLOAD [28] $end
$var wire 1 1 WDTLOAD [27] $end
$var wire 1 2 WDTLOAD [26] $end
$var wire 1 3 WDTLOAD [25] $end
$var wire 1 4 WDTLOAD [24] $end
$var wire 1 5 WDTLOAD [23] $end
$var wire 1 6 WDTLOAD [22] $end
$var wire 1 7 WDTLOAD [21] $end
$var wire 1 8 WDTLOAD [20] $end
$var wire 1 9 WDTLOAD [19] $end
$var wire 1 : WDTLOAD [18] $end
$var wire 1 ; WDTLOAD [17] $end
$var wire 1 < WDTLOAD [16] $end
$var wire 1 = WDTLOAD [15] $end
$var wire 1 > WDTLOAD [14] $end
$var wire 1 ? WDTLOAD [13] $end
$var wire 1 @ WDTLOAD [12] $end
$var wire 1 A WDTLOAD [11] $end
$var wire 1 B WDTLOAD [10] $end
$var wire 1 C WDTLOAD [9] $end
$var wire 1 D WDTLOAD [8] $end
$var wire 1 E WDTLOAD [7] $end
$var wire 1 F WDTLOAD [6] $end
$var wire 1 G WDTLOAD [5] $end
$var wire 1 H WDTLOAD [4] $end
$var wire 1 I WDTLOAD [3] $end
$var wire 1 J WDTLOAD [2] $end
$var wire 1 K WDTLOAD [1] $end
$var wire 1 L WDTLOAD [0] $end
$var reg 1 M WDTTO $end
$var reg 32 N WDTMR [31:0] $end
$upscope $end
$upscope $end
$enddefinitions $end
#0
$dumpvars
1"
1#
0$
b0 %
0&
b0 '
bx (
0M
b0 N
b1010 !
b0 )
0L
0K
0J
0I
0H
0G
0F
0E
0D
0C
0B
0A
0@
0?
0>
0=
0<
0;
0:
09
08
07
06
05
04
03
02
01
00
0/
0.
0-
0,
1+
1*
$end
#5000
0"
0*
#10000
0#
1$
1"
1,
0+
1*
b11111111111111111111111111111111 N
1M
1&
b11111111111111111111111111111111 '
#15000
0"
0*
#20000
b11011110101011011011111011101111 %
1"
1L
1K
1J
1I
1G
1F
1E
1C
1B
1A
1@
1?
1=
1<
1:
19
17
15
13
12
11
10
1.
1-
1*
b11011110101011011011111011101111 N
0M
0&
b11011110101011011011111011101111 '
#25000
0"
0*
#30000
1"
1*
b11011110101011011011111011101110 N
b11011110101011011011111011101110 '
#35000
0"
0*
#40000
1"
1*
b11011110101011011011111011101101 N
b11011110101011011011111011101101 '
#45000
0"
0*
#50000
1"
1*
b11011110101011011011111011101100 N
b11011110101011011011111011101100 '
#55000
0"
0*
#60000
1"
1*
b11011110101011011011111011101011 N
b11011110101011011011111011101011 '
#65000
0"
0*
#70000
b11011110101011011011111011101011 (
1"
1*
b11011110101011011011111011101010 N
b11011110101011011011111011101010 '
#75000
0"
0*
#80000
1"
1*
b11011110101011011011111011101001 N
b11011110101011011011111011101001 '
#85000
0"
0*
#90000
1"
1*
b11011110101011011011111011101000 N
b11011110101011011011111011101000 '
#95000
0"
0*
#100000
1"
1*
b11011110101011011011111011100111 N
b11011110101011011011111011100111 '
#105000
0"
0*
#110000
1"
1*
b11011110101011011011111011100110 N
b11011110101011011011111011100110 '
#115000
0"
0*
#120000
1#
0$
1"
0,
1+
1*
b0 N
1M
0M
b0 '
#125000
0"
0*
#130000
0#
1"
0+
1*
b11011110101011011011111011101111 N
b11011110101011011011111011101111 '
#135000
0"
0*
#140000
b10111010101110101100101011001010 %
1"
0L
0J
0G
0B
0@
0?
1>
0<
1;
0:
18
02
1/
0.
1*
b10111010101110101100101011001010 N
b10111010101110101100101011001010 '
#145000
0"
0*
#150000
1"
1*
#155000
0"
0*
#160000
1"
1*
#165000
0"
0*
#170000
1"
1*
#175000
0"
0*
#180000
1"
1*
#185000
0"
0*
#190000
b10111010101110101100101011001010 (
1"
1*
#195000
0"
0*
#200000
1"
1*
#205000
0"
0*
#210000
1"
1*
#215000
0"
0*
#220000
1"
1*
#225000
0"
0*
#230000
1"
1*
#235000
0"
0*
#240000
1#
1"
1+
1*
b0 N
1M
0M
b0 '
#245000
0"
0*
#250000
0#
1$
1"
1,
0+
1*
b11111111111111111111111111111111 N
1M
1&
b11111111111111111111111111111111 '
#255000
0"
0*
#260000
b11001010101110101100101011001010 %
1"
00
0/
1.
1*
b11001010101110101100101011001010 N
0M
0&
b11001010101110101100101011001010 '
#265000
0"
0*
#270000
1"
1*
b11001010101110101100101011001001 N
b11001010101110101100101011001001 '
#275000
0"
0*
#280000
1"
1*
b11001010101110101100101011001000 N
b11001010101110101100101011001000 '
#285000
0"
0*
#290000
1"
1*
b11001010101110101100101011000111 N
b11001010101110101100101011000111 '
#295000
0"
0*
#300000
1"
1*
b11001010101110101100101011000110 N
b11001010101110101100101011000110 '
#305000
0"
0*
#310000
b11001010101110101100101011000110 (
1"
1*
b11001010101110101100101011000101 N
b11001010101110101100101011000101 '
#315000
0"
0*
#320000
1"
1*
b11001010101110101100101011000100 N
b11001010101110101100101011000100 '
#325000
0"
0*
#330000
1"
1*
b11001010101110101100101011000011 N
b11001010101110101100101011000011 '
#335000
0"
0*
#340000
1"
1*
b11001010101110101100101011000010 N
b11001010101110101100101011000010 '
#345000
0"
0*
#350000
1"
1*
b11001010101110101100101011000001 N
b11001010101110101100101011000001 '
#355000
0"
0*
#360000
1#
0$
1"
0,
1+
1*
b0 N
1M
0M
b0 '
#365000
0"
0*
#370000
0#
1"
0+
1*
b11001010101110101100101011001010 N
b11001010101110101100101011001010 '
#375000
0"
0*
#380000
1$
1"
1,
1*
b11001010101110101100101011001001 N
b11001010101110101100101011001001 '
#385000
0"
0*
#390000
1"
1*
b11001010101110101100101011001000 N
b11001010101110101100101011001000 '
#395000
0"
0*
#400000
1"
1*
b11001010101110101100101011000111 N
b11001010101110101100101011000111 '
#405000
0"
0*
#410000
1"
1*
b11001010101110101100101011000110 N
b11001010101110101100101011000110 '
#415000
0"
0*
#420000
1"
1*
b11001010101110101100101011000101 N
b11001010101110101100101011000101 '
#425000
0"
0*
#430000
b11001010101110101100101011000101 (
1"
1*
b11001010101110101100101011000100 N
b11001010101110101100101011000100 '
#435000
0"
0*
#440000
1"
1*
b11001010101110101100101011000011 N
b11001010101110101100101011000011 '
#445000
0"
0*
#450000
1"
1*
b11001010101110101100101011000010 N
b11001010101110101100101011000010 '
#455000
0"
0*
#460000
1"
1*
b11001010101110101100101011000001 N
b11001010101110101100101011000001 '
#465000
0"
0*
#470000
1"
1*
b11001010101110101100101011000000 N
b11001010101110101100101011000000 '
